MANIFEST.in
README.md
requirements.txt
setup.py
aliyunpy/__init__.py
aliyunpy/exceptions.py
aliyunpy.egg-info/PKG-INFO
aliyunpy.egg-info/SOURCES.txt
aliyunpy.egg-info/dependency_links.txt
aliyunpy.egg-info/requires.txt
aliyunpy.egg-info/top_level.txt
aliyunpy/client/__init__.py
aliyunpy/client/base.py
aliyunpy/client/monkey.py
aliyunpy/client/utils.py
aliyunpy/client/api/__init__.py
aliyunpy/client/api/base.py
aliyunpy/client/api/bss.py
aliyunpy/client/api/cs.py
aliyunpy/client/api/dns.py
aliyunpy/client/api/drds.py
aliyunpy/client/api/ecs.py
aliyunpy/client/api/kms.py
aliyunpy/client/api/log.py
aliyunpy/client/api/ons.py
aliyunpy/client/api/oss.py
aliyunpy/client/api/pvtz.py
aliyunpy/client/api/ram.py
aliyunpy/client/api/rds.py
aliyunpy/client/api/redis.py
aliyunpy/client/api/slb.py
aliyunpy/client/api/vpc.py
aliyunpy/client/api/waf.py