Metadata-Version: 1.0
Name: aliyunpy
Version: 1.0.0
Summary: aliyun sdk tools
Home-page: UNKNOWN
Author: jokimina
Author-email: jokimina@163.com
License: UNKNOWN
Platform: UNKNOWN
